.gitignore
MANIFEST.in
README.md
requirements.txt
setup.py
frida_rpc/__init__.py
frida_rpc/app.py
frida_rpc/defaults.cfg
frida_rpc/exceptions.py
frida_rpc/lib.py
frida_rpc/routes.py
frida_rpc/system.py
frida_rpc/util.py
frida_rpc.egg-info/PKG-INFO
frida_rpc.egg-info/SOURCES.txt
frida_rpc.egg-info/dependency_links.txt
frida_rpc.egg-info/not-zip-safe
frida_rpc.egg-info/requires.txt
frida_rpc.egg-info/top_level.txt