Metadata-Version: 2.1
Name: frida-rpc
Version: 0.1.2
Summary: Expose frida RPC as a service you can access over the web or network
Home-page: https://github.com/ydaniels/frida-web-rpc
Author: Yomi D
Author-email: yomid4all@gmail.com
License: MIT
Keywords: frida rpc web network internet reverse engineering
Platform: UNKNOWN
Classifier: License :: OSI Approved :: MIT License
Classifier: Programming Language :: Python :: 3.6
